viktor_feedback_manager/__init__.py
viktor_feedback_manager/feedback_entity_controller.py
viktor_feedback_manager/feedback_manager_entity_controller.py
viktor_feedback_manager-0.0.1.dist-info/LICENSE
viktor_feedback_manager-0.0.1.dist-info/METADATA
viktor_feedback_manager-0.0.1.dist-info/WHEEL
viktor_feedback_manager-0.0.1.dist-info/top_level.txt
viktor_feedback_manager-0.0.1.dist-info/RECORD
