Metadata-Version: 2.1
Name: viktor_feedback_manager
Version: 0.0.1
Summary: Feedback manager for VIKTOR applications
Author-email: "S.J. van der Meer" <svandermeer@viktor.ai>
Maintainer-email: "S.J. van der Meer" <svandermeer@viktor.ai>
License: MIT License
Project-URL: Homepage, https://github.com/viktor-platform/viktor_feedback_manager
Project-URL: Bug Reports, https://github.com/viktor-platform/viktor_feedback_manager/issues
Requires-Python: >=3.7
License-File: LICENSE
Requires-Dist: viktor
Requires-Dist: pandas <2.0.0
Requires-Dist: requests
Requires-Dist: beautifulsoup4
Provides-Extra: dev
Requires-Dist: black ; extra == 'dev'
Requires-Dist: isort ; extra == 'dev'
Requires-Dist: pylint ; extra == 'dev'
